voxel_sdk/__init__.py
voxel_sdk/ble.py
voxel_sdk/commands.py
voxel_sdk/device_controller.py
voxel_sdk/serial.py
voxel_sdk/voxel.py
voxel_sdk-0.1.1.dist-info/METADATA
voxel_sdk-0.1.1.dist-info/WHEEL
voxel_sdk-0.1.1.dist-info/licenses/LICENSE
voxel_sdk-0.1.1.dist-info/RECORD
