Metadata-Version: 2.4
Name: voxel-sdk
Version: 0.1.1
Summary: SDK for Voxel
Project-URL: Homepage, https://github.com/physicalinc/voxel-sdk
Project-URL: Repository, https://github.com/physicalinc/voxel-sdk
Author-email: "Physical Automation, Inc" <contact@physical.inc>
License: MIT License
License-File: LICENSE
Classifier: Development Status :: 3 - Alpha
Classifier: Intended Audience :: Developers
Classifier: License :: OSI Approved :: MIT License
Classifier: Programming Language :: Python :: 3
Classifier: Programming Language :: Python :: 3.8
Classifier: Programming Language :: Python :: 3.9
Classifier: Programming Language :: Python :: 3.10
Classifier: Programming Language :: Python :: 3.11
Classifier: Programming Language :: Python :: 3.12
Requires-Python: >=3.8
Requires-Dist: bleak>=0.22.0
Requires-Dist: numpy>=1.23.0
Requires-Dist: opencv-python>=4.8.0
Requires-Dist: pyserial>=3.5
Provides-Extra: all
Requires-Dist: bleak>=0.22.0; extra == 'all'
Requires-Dist: numpy>=1.23.0; extra == 'all'
Requires-Dist: opencv-python>=4.8.0; extra == 'all'
Requires-Dist: pyserial>=3.5; extra == 'all'
Provides-Extra: ble
Requires-Dist: bleak>=0.22.0; extra == 'ble'
Provides-Extra: serial
Requires-Dist: pyserial>=3.5; extra == 'serial'
Provides-Extra: viz
Requires-Dist: numpy>=1.23.0; extra == 'viz'
Requires-Dist: opencv-python>=4.8.0; extra == 'viz'
